Metadata-Version: 1.1
Name: PyCapture
Version: 0.0.0
Summary: Take a screenshot from Python Script
Home-page: https://github.com/Manato0x2cc/PyCapture
Author: Manato0x2cc
Author-email: manato0x2cc@gmail.com
License: Apache
Keywords: gui screenshot capture img image
Platform: UNKNOWN
Classifier: Environment :: MacOS X
Classifier: License :: OSI Approved :: BSD License
Classifier: Programming Language :: Python
Classifier: Programming Language :: Python :: 2
Classifier: Programming Language :: Python :: 2.5
Classifier: Programming Language :: Python :: 2.6
Classifier: Programming Language :: Python :: 2.7
Classifier: Programming Language :: Python :: 3
Classifier: Programming Language :: Python :: 3.1
Classifier: Programming Language :: Python :: 3.2
Classifier: Programming Language :: Python :: 3.3
Classifier: Programming Language :: Python :: 3.4
